gerbil_api_wrapper/__init__.py
gerbil_api_wrapper/gerbil.py
tests/__init__.py
tests/test_gerbil_api_wrapper.py
tests/test_gerbil_api_wrapper_live.py
gerbil_api_wrapper-1.0.3.dist-info/LICENSE
gerbil_api_wrapper-1.0.3.dist-info/METADATA
gerbil_api_wrapper-1.0.3.dist-info/WHEEL
gerbil_api_wrapper-1.0.3.dist-info/top_level.txt
gerbil_api_wrapper-1.0.3.dist-info/RECORD
