Metadata-Version: 2.1
Name: gerbil-api-wrapper
Version: 1.0.3
Summary: A package that provides wrapper functionality for the Gerbil Benchmark Service
Home-page: https://github.com/heinpa/GerbilExperimentApiWrapper
Author: Paul Heinze
Author-email: paul.heinze@student.hs-anhalt.de
Requires-Python: >=3.6
License-File: LICENSE
Requires-Dist: attrs
Requires-Dist: beautifulsoup4
Requires-Dist: bs4
Requires-Dist: certifi
Requires-Dist: charset-normalizer
Requires-Dist: decorator
Requires-Dist: idna
Requires-Dist: iniconfig
Requires-Dist: packaging
Requires-Dist: pluggy
Requires-Dist: py
Requires-Dist: pyparsing
Requires-Dist: pytest
Requires-Dist: requests
Requires-Dist: soupsieve
Requires-Dist: tomli
Requires-Dist: urllib3
Requires-Dist: validators
